README.rst
setup.py
rempycs/__init__.py
rempycs/rempycs.py
rempycs.egg-info/PKG-INFO
rempycs.egg-info/SOURCES.txt
rempycs.egg-info/dependency_links.txt
rempycs.egg-info/entry_points.txt
rempycs.egg-info/not-zip-safe
rempycs.egg-info/top_level.txt